{
  "id": "ETHUSDT_1762837421",
  "timestamp": "2025-11-11T13:03:41.99763+08:00",
  "symbol": "ETHUSDT",
  "prediction": {
    "symbol": "ETHUSDT",
    "direction": "up",
    "probability": 0.65,
    "expected_move": 2.5,
    "timeframe": "24h",
    "confidence": "medium",
    "reasoning": "RSI超卖且市场情绪悲观，但积累期提供低价买入机会。MACD和EMA显示中性趋势。",
    "key_factors": [
      "RSI超卖",
      "积累期低价买入机会",
      "市场情绪悲观"
    ],
    "risk_level": "medium",
    "worst_case": -1.5,
    "best_case": 3.5
  },
  "entry_price": 3572.59,
  "target_time": "2025-11-12T13:03:41.99763+08:00",
  "evaluated": false,
  "actual_move": 0,
  "actual_high": 0,
  "actual_low": 0,
  "is_correct": false,
  "accuracy": 0,
  "evaluated_time": "0001-01-01T00:00:00Z"
}