{
  "id": "ETHUSDT_1762460351",
  "timestamp": "2025-11-07T04:19:11.498998+08:00",
  "symbol": "ETHUSDT",
  "prediction": {
    "symbol": "ETHUSDT",
    "direction": "up",
    "probability": 0.76,
    "expected_move": 1.85,
    "timeframe": "4h",
    "confidence": "high",
    "reasoning": "市场技术面显示以太坊处于明显下行趋势，价格低于所有关键均线，RSI进入超卖区域，短期存在反弹修正动力。尽管整体趋势偏空，但量价背离与波动率收缩暗示下跌动能减弱，可能触发技术性反弹。账户层面夏普比率为负，系统表现略差，因此适度下调预测概率，但仍基于当前超卖信号维持看涨判断。历史反馈显示此类情境下短期反弹准确率中等偏上。",
    "key_factors": [
      "超卖反弹潜力",
      "量价背离信号",
      "波动率收缩突破"
    ],
    "risk_level": "medium",
    "worst_case": -1.2,
    "best_case": 3.5
  },
  "entry_price": 3312.52,
  "target_time": "2025-11-07T08:19:11.498997+08:00",
  "evaluated": true,
  "actual_move": -0.3344885464842455,
  "actual_high": 3335,
  "actual_low": 3285.97,
  "is_correct": false,
  "accuracy": 0,
  "evaluated_time": "2025-11-07T23:22:55.537777+08:00"
}